molspotter/__init__.py
molspotter/cli.py
molspotter/io.py
molspotter/molspotter.py
molspotter/spotters/__init__.py
molspotter/spotters/chembl_32.sp
molspotter/spotters/excapedb.sp
molspotter/spotters/papyrus_05.6.sp
molspotter-0.0.2.dist-info/LICENSE
molspotter-0.0.2.dist-info/METADATA
molspotter-0.0.2.dist-info/WHEEL
molspotter-0.0.2.dist-info/entry_points.txt
molspotter-0.0.2.dist-info/top_level.txt
molspotter-0.0.2.dist-info/RECORD
