Metadata-Version: 2.1
Name: molspotter
Version: 0.0.2
Summary: Identify silly molecules
Home-page: https://github.com/OlivierBeq/molspotter
Author: Olivier J. M. Béquignon
Author-email: "olivier.bequignon.maintainer@gmail.com"
Maintainer: Olivier J. M. Béquignon
Maintainer-email: "olivier.bequignon.maintainer@gmail.com"
Keywords: cheminformatics
Classifier: Development Status :: 5 - Production/Stable
Classifier: License :: OSI Approved :: MIT License
Classifier: Programming Language :: Python :: 3.10
Classifier: Programming Language :: Python :: 3.9
Classifier: Programming Language :: Python :: 3.8
License-File: LICENSE
Requires-Dist: rdkit
Requires-Dist: tqdm
Requires-Dist: click
Provides-Extra: docs
Requires-Dist: sphinx ; extra == 'docs'
Requires-Dist: sphinx-rtd-theme ; extra == 'docs'
Requires-Dist: sphinx-autodoc-typehints ; extra == 'docs'
Provides-Extra: testing
Requires-Dist: pytest ; extra == 'testing'
